{
  "skillId": "perimeter-2d-shapes",
  "atomType": "R",
  "theory": {
    "intro": "The perimeter is the total distance around the outside of a 2D shape. Add the lengths of all the sides.",
    "facts": [
      "Perimeter $=$ the sum of **all** side lengths.",
      "A square has $4$ equal sides, so $P = 4 \\times \\text{side}$.",
      "A rectangle has two pairs of equal sides, so $P = 2 \\times (\\text{length} + \\text{width})$."
    ],
    "steps": [
      "List every side length around the shape.",
      "Add them all together.",
      "Write the answer with the correct unit."
    ]
  },
  "practice": {
    "foundation": [
      { "q": "Find the perimeter of this square.", "a": "$20$ cm",
        "tikz": "\\begin{tikzpicture}[x=1cm,y=1cm]\n\\draw[thick] (0,0) rectangle (2.5,2.5);\n\\node[below] at (1.25,0) {$5\\text{ cm}$};\n\\end{tikzpicture}",
        "solution": [ { "math": "$4 \\times 5$", "note": "4 equal sides" }, { "math": "$= 20 \\text{ cm}$", "note": "" } ] },
      { "q": "Find the perimeter of this rectangle.", "a": "$22$ cm",
        "tikz": "\\begin{tikzpicture}[x=1cm,y=1cm]\n\\draw[thick] (0,0) rectangle (4,2);\n\\node[below] at (2,0) {$7\\text{ cm}$};\n\\node[right] at (4,1) {$4\\text{ cm}$};\n\\end{tikzpicture}",
        "solution": [ { "math": "$2 \\times (7 + 4)$", "note": "Two of each side" }, { "math": "$= 22 \\text{ cm}$", "note": "" } ] },
      { "q": "Find the perimeter of this rectangle.", "a": "$26$ m",
        "tikz": "\\begin{tikzpicture}[x=1cm,y=1cm]\n\\draw[thick] (0,0) rectangle (4,1.5);\n\\node[below] at (2,0) {$9\\text{ m}$};\n\\node[right] at (4,0.75) {$4\\text{ m}$};\n\\end{tikzpicture}",
        "solution": [ { "math": "$2 \\times (9 + 4)$", "note": "Two of each side" }, { "math": "$= 26 \\text{ m}$", "note": "" } ] },
      { "q": "Find the perimeter of this square.", "a": "$32$ cm",
        "tikz": "\\begin{tikzpicture}[x=1cm,y=1cm]\n\\draw[thick] (0,0) rectangle (2.5,2.5);\n\\node[below] at (1.25,0) {$8\\text{ cm}$};\n\\end{tikzpicture}",
        "solution": [ { "math": "$4 \\times 8$", "note": "4 equal sides" }, { "math": "$= 32 \\text{ cm}$", "note": "" } ] },
      { "q": "Find the perimeter of this triangle.", "a": "$12$ cm",
        "tikz": "\\begin{tikzpicture}[x=1cm,y=1cm]\n\\draw[thick] (0,0)--(4,0)--(2,2.2)--cycle;\n\\node[below] at (2,0) {$4\\text{ cm}$};\n\\node[left] at (0.8,1.2) {$4\\text{ cm}$};\n\\node[right] at (3.2,1.2) {$4\\text{ cm}$};\n\\end{tikzpicture}",
        "solution": [ { "math": "$4 + 4 + 4$", "note": "Add three sides" }, { "math": "$= 12 \\text{ cm}$", "note": "" } ] },
      { "q": "Find the perimeter of this triangle.", "a": "$15$ cm",
        "tikz": "\\begin{tikzpicture}[x=1cm,y=1cm]\n\\draw[thick] (0,0)--(4,0)--(1.4,2.4)--cycle;\n\\node[below] at (2,0) {$6\\text{ cm}$};\n\\node[left] at (0.5,1.2) {$4\\text{ cm}$};\n\\node[right] at (3,1.4) {$5\\text{ cm}$};\n\\end{tikzpicture}",
        "solution": [ { "math": "$6 + 4 + 5$", "note": "Add three sides" }, { "math": "$= 15 \\text{ cm}$", "note": "" } ] },
      { "q": "Find the perimeter of this rectangle.", "a": "$30$ cm",
        "tikz": "\\begin{tikzpicture}[x=1cm,y=1cm]\n\\draw[thick] (0,0) rectangle (4,2);\n\\node[below] at (2,0) {$10\\text{ cm}$};\n\\node[right] at (4,1) {$5\\text{ cm}$};\n\\end{tikzpicture}",
        "solution": [ { "math": "$2 \\times (10 + 5)$", "note": "Two of each side" }, { "math": "$= 30 \\text{ cm}$", "note": "" } ] },
      { "q": "Find the perimeter of this square.", "a": "$12$ m",
        "tikz": "\\begin{tikzpicture}[x=1cm,y=1cm]\n\\draw[thick] (0,0) rectangle (2.5,2.5);\n\\node[below] at (1.25,0) {$3\\text{ m}$};\n\\end{tikzpicture}",
        "solution": [ { "math": "$4 \\times 3$", "note": "4 equal sides" }, { "math": "$= 12 \\text{ m}$", "note": "" } ] },
      { "q": "Find the perimeter of this triangle.", "a": "$24$ cm",
        "tikz": "\\begin{tikzpicture}[x=1cm,y=1cm]\n\\draw[thick] (0,0)--(4,0)--(4,3)--cycle;\n\\node[below] at (2,0) {$8\\text{ cm}$};\n\\node[right] at (4,1.5) {$6\\text{ cm}$};\n\\node[above left] at (2,1.7) {$10\\text{ cm}$};\n\\end{tikzpicture}",
        "solution": [ { "math": "$8 + 6 + 10$", "note": "Add three sides" }, { "math": "$= 24 \\text{ cm}$", "note": "" } ] },
      { "q": "Find the perimeter of this rectangle.", "a": "$18$ cm",
        "tikz": "\\begin{tikzpicture}[x=1cm,y=1cm]\n\\draw[thick] (0,0) rectangle (3.5,2);\n\\node[below] at (1.75,0) {$6\\text{ cm}$};\n\\node[right] at (3.5,1) {$3\\text{ cm}$};\n\\end{tikzpicture}",
        "solution": [ { "math": "$2 \\times (6 + 3)$", "note": "Two of each side" }, { "math": "$= 18 \\text{ cm}$", "note": "" } ] }
    ],
    "development": [
      { "q": "Find the perimeter of this rectangle.", "a": "$46$ cm",
        "tikz": "\\begin{tikzpicture}[x=1cm,y=1cm]\n\\draw[thick] (0,0) rectangle (4,1.8);\n\\node[below] at (2,0) {$15\\text{ cm}$};\n\\node[right] at (4,0.9) {$8\\text{ cm}$};\n\\end{tikzpicture}",
        "solution": [ { "math": "$2 \\times (15 + 8)$", "note": "Two of each side" }, { "math": "$= 46 \\text{ cm}$", "note": "" } ] },
      { "q": "Find the perimeter of this scalene triangle.", "a": "$33$ cm",
        "tikz": "\\begin{tikzpicture}[x=1cm,y=1cm]\n\\draw[thick] (0,0)--(4.5,0)--(1.2,2.4)--cycle;\n\\node[below] at (2.25,0) {$13\\text{ cm}$};\n\\node[left] at (0.4,1.2) {$9\\text{ cm}$};\n\\node[right] at (3.2,1.4) {$11\\text{ cm}$};\n\\end{tikzpicture}",
        "solution": [ { "math": "$13 + 9 + 11$", "note": "Add three sides" }, { "math": "$= 33 \\text{ cm}$", "note": "" } ] },
      { "q": "A square has side $14$ m. Find its perimeter.", "a": "$56$ m",
        "tikz": "\\begin{tikzpicture}[x=1cm,y=1cm]\n\\draw[thick] (0,0) rectangle (2.5,2.5);\n\\node[below] at (1.25,0) {$14\\text{ m}$};\n\\end{tikzpicture}",
        "solution": [ { "math": "$4 \\times 14$", "note": "4 equal sides" }, { "math": "$= 56 \\text{ m}$", "note": "" } ] },
      { "q": "Find the perimeter of this rectangle.", "a": "$64$ m",
        "tikz": "\\begin{tikzpicture}[x=1cm,y=1cm]\n\\draw[thick] (0,0) rectangle (4,1.5);\n\\node[below] at (2,0) {$20\\text{ m}$};\n\\node[right] at (4,0.75) {$12\\text{ m}$};\n\\end{tikzpicture}",
        "solution": [ { "math": "$2 \\times (20 + 12)$", "note": "Two of each side" }, { "math": "$= 64 \\text{ m}$", "note": "" } ] },
      { "q": "An equilateral triangle has perimeter shown by side $7$ cm. Find the perimeter.", "a": "$21$ cm",
        "tikz": "\\begin{tikzpicture}[x=1cm,y=1cm]\n\\draw[thick] (0,0)--(4,0)--(2,3.4)--cycle;\n\\node[below] at (2,0) {$7\\text{ cm}$};\n\\node[left] at (0.8,1.7) {$7\\text{ cm}$};\n\\node[right] at (3.2,1.7) {$7\\text{ cm}$};\n\\end{tikzpicture}",
        "solution": [ { "math": "$3 \\times 7$", "note": "3 equal sides" }, { "math": "$= 21 \\text{ cm}$", "note": "" } ] },
      { "q": "Find the perimeter of this isosceles triangle (two sides $12$ cm, base $8$ cm).", "a": "$32$ cm",
        "tikz": "\\begin{tikzpicture}[x=1cm,y=1cm]\n\\draw[thick] (0,0)--(4,0)--(2,3.2)--cycle;\n\\node[below] at (2,0) {$8\\text{ cm}$};\n\\node[left] at (0.8,1.6) {$12\\text{ cm}$};\n\\node[right] at (3.2,1.6) {$12\\text{ cm}$};\n\\end{tikzpicture}",
        "solution": [ { "math": "$12 + 12 + 8$", "note": "Two equal sides plus base" }, { "math": "$= 32 \\text{ cm}$", "note": "" } ] },
      { "q": "A rectangle has length $25$ cm and width $9$ cm. Find its perimeter.", "a": "$68$ cm",
        "tikz": "\\begin{tikzpicture}[x=1cm,y=1cm]\n\\draw[thick] (0,0) rectangle (4,1.4);\n\\node[below] at (2,0) {$25\\text{ cm}$};\n\\node[right] at (4,0.7) {$9\\text{ cm}$};\n\\end{tikzpicture}",
        "solution": [ { "math": "$2 \\times (25 + 9)$", "note": "Two of each side" }, { "math": "$= 68 \\text{ cm}$", "note": "" } ] },
      { "q": "Find the total perimeter of this L-shape (all right angles).", "a": "$24$ cm",
        "tikz": "\\begin{tikzpicture}[x=0.7cm,y=0.7cm]\n\\draw[thick] (0,0)--(6,0)--(6,2)--(2,2)--(2,4)--(0,4)--cycle;\n\\node[below] at (3,0) {$6$};\n\\node[right] at (6,1) {$2$};\n\\node[above] at (4,2) {$4$};\n\\node[right] at (2,3) {$2$};\n\\node[above] at (1,4) {$2$};\n\\node[left] at (0,2) {$4$};\n\\end{tikzpicture}",
        "solution": [ { "math": "$6+2+4+2+2+4$", "note": "Add every side (cm)" }, { "math": "$= 24 \\text{ cm}$", "note": "" } ] },
      { "q": "Find the perimeter of this triangle with sides $9$ cm, $12$ cm and $15$ cm.", "a": "$36$ cm",
        "tikz": "\\begin{tikzpicture}[x=1cm,y=1cm]\n\\draw[thick] (0,0)--(4,0)--(0,3)--cycle;\n\\node[below] at (2,0) {$12\\text{ cm}$};\n\\node[left] at (0,1.5) {$9\\text{ cm}$};\n\\node[above right] at (2,1.7) {$15\\text{ cm}$};\n\\end{tikzpicture}",
        "solution": [ { "math": "$9 + 12 + 15$", "note": "Add three sides" }, { "math": "$= 36 \\text{ cm}$", "note": "" } ] },
      { "q": "Find the perimeter of this rectangle.", "a": "$54$ mm",
        "tikz": "\\begin{tikzpicture}[x=1cm,y=1cm]\n\\draw[thick] (0,0) rectangle (4,2.2);\n\\node[below] at (2,0) {$16\\text{ mm}$};\n\\node[right] at (4,1.1) {$11\\text{ mm}$};\n\\end{tikzpicture}",
        "solution": [ { "math": "$2 \\times (16 + 11)$", "note": "Two of each side" }, { "math": "$= 54 \\text{ mm}$", "note": "" } ] }
    ],
    "mastery": [
      { "q": "A square has perimeter $36$ cm. What is the length of one side?", "a": "$9$ cm",
        "solution": [ { "math": "$36 \\div 4$", "note": "4 equal sides" }, { "math": "$= 9 \\text{ cm}$", "note": "" } ] },
      { "q": "A rectangle has perimeter $30$ cm and width $6$ cm. Find its length.", "a": "$9$ cm",
        "solution": [ { "math": "$30 \\div 2 = 15$", "note": "length + width" }, { "math": "$15 - 6 = 9 \\text{ cm}$", "note": "" } ] },
      { "q": "A rectangular paddock is $40$ m by $30$ m. Fencing costs \\$8 per metre. What is the cost to fence it?", "a": "\\$1120",
        "solution": [ { "math": "$2 \\times (40 + 30) = 140 \\text{ m}$", "note": "Perimeter" }, { "math": "$140 \\times 8 = \\$1120$", "note": "" } ] },
      { "q": "An equilateral triangle has perimeter $54$ cm. Find one side.", "a": "$18$ cm",
        "solution": [ { "math": "$54 \\div 3$", "note": "3 equal sides" }, { "math": "$= 18 \\text{ cm}$", "note": "" } ] },
      { "q": "An isosceles triangle has two equal sides of $13$ cm and a perimeter of $34$ cm. Find the base.", "a": "$8$ cm",
        "solution": [ { "math": "$2 \\times 13 = 26$", "note": "Two equal sides" }, { "math": "$34 - 26 = 8 \\text{ cm}$", "note": "" } ] },
      { "q": "Two identical squares of side $5$ cm are joined to form a rectangle. Find the perimeter of the rectangle.", "a": "$30$ cm",
        "tikz": "\\begin{tikzpicture}[x=0.8cm,y=0.8cm]\n\\draw[thick] (0,0) rectangle (4,2);\n\\draw (2,0)--(2,2);\n\\node[below] at (2,0) {$10\\text{ cm}$};\n\\node[right] at (4,1) {$5\\text{ cm}$};\n\\end{tikzpicture}",
        "solution": [ { "math": "$\\text{Rectangle } 10 \\times 5$", "note": "Two squares side by side" }, { "math": "$2 \\times (10 + 5) = 30 \\text{ cm}$", "note": "" } ] },
      { "q": "A rectangle is twice as long as it is wide. Its perimeter is $48$ cm. Find its length.", "a": "$16$ cm",
        "solution": [ { "math": "$2(2w + w) = 48$", "note": "length $= 2w$" }, { "math": "$6w = 48 \\Rightarrow w = 8,\\ \\ell = 16 \\text{ cm}$", "note": "" } ] },
      { "q": "A square garden of side $12$ m has a path around it. Find the perimeter of the garden.", "a": "$48$ m",
        "solution": [ { "math": "$4 \\times 12$", "note": "4 equal sides" }, { "math": "$= 48 \\text{ m}$", "note": "" } ] },
      { "q": "A rectangle has perimeter $50$ cm. Its length is $4$ cm more than its width. Find the width.", "a": "$10.5$ cm",
        "solution": [ { "math": "$2(w + 4 + w) = 50$", "note": "length $= w + 4$" }, { "math": "$4w + 8 = 50 \\Rightarrow w = 10.5 \\text{ cm}$", "note": "" } ] },
      { "q": "Find the perimeter of this L-shape (lengths in metres).", "a": "$28$ m",
        "tikz": "\\begin{tikzpicture}[x=0.6cm,y=0.6cm]\n\\draw[thick] (0,0)--(8,0)--(8,3)--(3,3)--(3,5)--(0,5)--cycle;\n\\node[below] at (4,0) {$8$};\n\\node[right] at (8,1.5) {$3$};\n\\node[above] at (5.5,3) {$5$};\n\\node[right] at (3,4) {$2$};\n\\node[above] at (1.5,5) {$3$};\n\\node[left] at (0,2.5) {$5$};\n\\end{tikzpicture}",
        "solution": [ { "math": "$8+3+5+2+3+5$", "note": "Add every side (m)" }, { "math": "$= 28 \\text{ m}$", "note": "" } ] }
    ]
  }
}
