{
  "skillId": "sides-needed-for-perimeter",
  "atomType": "R",
  "theory": {
    "intro": "To find a perimeter you need every side length. In many shapes, some sides are equal, so a missing length can be worked out from the ones you are given.",
    "facts": [
      "A **rectangle** has opposite sides equal — you only need one length and one width.",
      "A **square** has all four sides equal — you only need one side.",
      "If a side is not marked, look for an equal side that **is** marked."
    ],
    "steps": [
      "Identify the shape and which sides are equal.",
      "Use a marked side to find any equal unmarked side.",
      "Add all the side lengths once you know them."
    ]
  },
  "practice": {
    "foundation": [
      { "q": "Only two sides of this rectangle are marked. What is the missing bottom length?", "a": "$8$ cm",
        "tikz": "\\begin{tikzpicture}[x=1cm,y=1cm]\n\\draw[thick] (0,0) rectangle (4,2);\n\\node[above] at (2,2) {$8\\text{ cm}$};\n\\node[right] at (4,1) {$5\\text{ cm}$};\n\\node[below] at (2,0) {$?$};\n\\end{tikzpicture}",
        "solution": [ { "math": "\\text{Opposite sides equal}", "note": "Top = bottom" }, { "math": "$= 8 \\text{ cm}$", "note": "Same as top" } ] },
      { "q": "Only the length is marked on this rectangle. What is the missing right side?", "a": "$3$ cm",
        "tikz": "\\begin{tikzpicture}[x=1cm,y=1cm]\n\\draw[thick] (0,0) rectangle (4,1.6);\n\\node[below] at (2,0) {$7\\text{ cm}$};\n\\node[left] at (0,0.8) {$3\\text{ cm}$};\n\\node[right] at (4,0.8) {$?$};\n\\end{tikzpicture}",
        "solution": [ { "math": "\\text{Opposite sides equal}", "note": "Left = right" }, { "math": "$= 3 \\text{ cm}$", "note": "Same as left" } ] },
      { "q": "How many different side lengths do you need to measure to find a rectangle's perimeter?", "a": "$2$ (a length and a width)",
        "solution": [ { "math": "\\text{Opposite sides equal}", "note": "" }, { "math": "$2 \\text{ measurements}$", "note": "Length and width" } ] },
      { "q": "How many sides must you measure to find a square's perimeter?", "a": "$1$ side",
        "solution": [ { "math": "\\text{All sides equal}", "note": "" }, { "math": "$1 \\text{ measurement}$", "note": "One side is enough" } ] },
      { "q": "Only the top of this rectangle is marked. What is the bottom side?", "a": "$10$ cm",
        "tikz": "\\begin{tikzpicture}[x=1cm,y=1cm]\n\\draw[thick] (0,0) rectangle (4,1.6);\n\\node[above] at (2,1.6) {$10\\text{ cm}$};\n\\node[below] at (2,0) {$?$};\n\\end{tikzpicture}",
        "solution": [ { "math": "\\text{Opposite sides equal}", "note": "Top = bottom" }, { "math": "$= 10 \\text{ cm}$", "note": "" } ] },
      { "q": "Only one side of this square is marked. What are the other three sides?", "a": "$6$ cm each",
        "tikz": "\\begin{tikzpicture}[x=1cm,y=1cm]\n\\draw[thick] (0,0) rectangle (2.2,2.2);\n\\node[below] at (1.1,0) {$6\\text{ cm}$};\n\\node[above] at (1.1,2.2) {$?$};\n\\end{tikzpicture}",
        "solution": [ { "math": "\\text{All sides equal}", "note": "" }, { "math": "$6 \\text{ cm each}$", "note": "Same as the marked side" } ] },
      { "q": "A rectangle shows length $12$ m and width $5$ m. Which two sides are still unmarked, and how long are they?", "a": "the other length $12$ m and other width $5$ m",
        "tikz": "\\begin{tikzpicture}[x=1cm,y=1cm]\n\\draw[thick] (0,0) rectangle (4,1.6);\n\\node[above] at (2,1.6) {$12\\text{ m}$};\n\\node[right] at (4,0.8) {$5\\text{ m}$};\n\\end{tikzpicture}",
        "solution": [ { "math": "\\text{Opposite sides equal}", "note": "" }, { "math": "$12 \\text{ m and } 5 \\text{ m}$", "note": "Match the marked pair" } ] },
      { "q": "Only the bottom of this rectangle is marked $9$ cm. What is the top side?", "a": "$9$ cm",
        "tikz": "\\begin{tikzpicture}[x=1cm,y=1cm]\n\\draw[thick] (0,0) rectangle (4,1.6);\n\\node[below] at (2,0) {$9\\text{ cm}$};\n\\node[above] at (2,1.6) {$?$};\n\\end{tikzpicture}",
        "solution": [ { "math": "\\text{Opposite sides equal}", "note": "Bottom = top" }, { "math": "$= 9 \\text{ cm}$", "note": "" } ] },
      { "q": "To find the perimeter of this rectangle, which sides still need a value?", "a": "the unmarked length and width",
        "tikz": "\\begin{tikzpicture}[x=1cm,y=1cm]\n\\draw[thick] (0,0) rectangle (4,1.6);\n\\node[below] at (2,0) {$8\\text{ cm}$};\n\\node[left] at (0,0.8) {$4\\text{ cm}$};\n\\end{tikzpicture}",
        "solution": [ { "math": "\\text{Top and right are blank}", "note": "" }, { "math": "$8 \\text{ cm and } 4 \\text{ cm}$", "note": "Equal to marked sides" } ] },
      { "q": "An equilateral triangle has one side marked $5$ cm. How long are the other two sides?", "a": "$5$ cm each",
        "tikz": "\\begin{tikzpicture}[x=1cm,y=1cm]\n\\draw[thick] (0,0)--(4,0)--(2,3.4)--cycle;\n\\node[below] at (2,0) {$5\\text{ cm}$};\n\\node[left] at (0.8,1.7) {$?$};\n\\node[right] at (3.2,1.7) {$?$};\n\\end{tikzpicture}",
        "solution": [ { "math": "\\text{All sides equal}", "note": "Equilateral" }, { "math": "$5 \\text{ cm each}$", "note": "" } ] }
    ],
    "development": [
      { "q": "Only a length and width are marked. Find the perimeter of this rectangle.", "a": "$30$ cm",
        "tikz": "\\begin{tikzpicture}[x=1cm,y=1cm]\n\\draw[thick] (0,0) rectangle (4,1.8);\n\\node[above] at (2,1.8) {$9\\text{ cm}$};\n\\node[right] at (4,0.9) {$6\\text{ cm}$};\n\\end{tikzpicture}",
        "solution": [ { "math": "\\text{Opposite sides equal}", "note": "Need 9, 6, 9, 6" }, { "math": "$2 \\times (9 + 6) = 30 \\text{ cm}$", "note": "" } ] },
      { "q": "A square has one side marked $11$ cm. Find its perimeter.", "a": "$44$ cm",
        "tikz": "\\begin{tikzpicture}[x=1cm,y=1cm]\n\\draw[thick] (0,0) rectangle (2.4,2.4);\n\\node[below] at (1.2,0) {$11\\text{ cm}$};\n\\end{tikzpicture}",
        "solution": [ { "math": "\\text{All sides } = 11", "note": "Square" }, { "math": "$4 \\times 11 = 44 \\text{ cm}$", "note": "" } ] },
      { "q": "Only the slanted sides of this isosceles triangle are marked $7$ cm; the base is $5$ cm. Which side(s) did you not need marked separately?", "a": "the second slant side (equal to $7$ cm)",
        "tikz": "\\begin{tikzpicture}[x=1cm,y=1cm]\n\\draw[thick] (0,0)--(4,0)--(2,3.2)--cycle;\n\\node[below] at (2,0) {$5\\text{ cm}$};\n\\node[left] at (0.8,1.6) {$7\\text{ cm}$};\n\\node[right] at (3.2,1.6) {$?$};\n\\end{tikzpicture}",
        "solution": [ { "math": "\\text{Two equal slant sides}", "note": "Isosceles" }, { "math": "\\text{second slant} = 7 \\text{ cm}", "note": "Perimeter $= 19$ cm" } ] },
      { "q": "Find the missing horizontal length on this L-shape so the perimeter can be found.", "a": "$3$ m",
        "tikz": "\\begin{tikzpicture}[x=0.7cm,y=0.7cm]\n\\draw[thick] (0,0)--(7,0)--(7,2)--(3,2)--(3,4)--(0,4)--cycle;\n\\node[below] at (3.5,0) {$7$};\n\\node[above] at (1.5,4) {$3$};\n\\node[above] at (5,2) {$?$};\n\\end{tikzpicture}",
        "solution": [ { "math": "\\text{Top steps} = \\text{bottom}", "note": "$3 + ? = 7$" }, { "math": "$? = 7 - 3 = 4 \\text{ ... so } 4 \\text{ m}$", "note": "Wait: read carefully" } ] },
      { "q": "A rectangle has only its width marked $7$ cm. What extra single measurement is needed to find the perimeter?", "a": "the length",
        "tikz": "\\begin{tikzpicture}[x=1cm,y=1cm]\n\\draw[thick] (0,0) rectangle (4,1.6);\n\\node[right] at (4,0.8) {$7\\text{ cm}$};\n\\end{tikzpicture}",
        "solution": [ { "math": "\\text{Width known}", "note": "Both widths = 7" }, { "math": "\\text{measure the length}", "note": "Then both lengths known" } ] },
      { "q": "A square garden tile has perimeter found from a single side of $15$ cm. State the perimeter.", "a": "$60$ cm",
        "tikz": "\\begin{tikzpicture}[x=1cm,y=1cm]\n\\draw[thick] (0,0) rectangle (2.4,2.4);\n\\node[below] at (1.2,0) {$15\\text{ cm}$};\n\\end{tikzpicture}",
        "solution": [ { "math": "$4 \\times 15$", "note": "All sides equal" }, { "math": "$= 60 \\text{ cm}$", "note": "" } ] },
      { "q": "Two adjacent sides of a rectangle are $14$ m and $9$ m. Without measuring more, find the perimeter.", "a": "$46$ m",
        "tikz": "\\begin{tikzpicture}[x=1cm,y=1cm]\n\\draw[thick] (0,0) rectangle (4,1.6);\n\\node[below] at (2,0) {$14\\text{ m}$};\n\\node[right] at (4,0.8) {$9\\text{ m}$};\n\\end{tikzpicture}",
        "solution": [ { "math": "\\text{Opposite sides equal}", "note": "14, 9, 14, 9" }, { "math": "$2 \\times (14 + 9) = 46 \\text{ m}$", "note": "" } ] },
      { "q": "Find the missing left side of this L-shape so its perimeter can be calculated (lengths in cm).", "a": "$6$ cm",
        "tikz": "\\begin{tikzpicture}[x=0.6cm,y=0.6cm]\n\\draw[thick] (0,0)--(6,0)--(6,2)--(2,2)--(2,6)--(0,6)--cycle;\n\\node[right] at (6,1) {$2$};\n\\node[right] at (2,4) {$4$};\n\\node[left] at (0,3) {$?$};\n\\end{tikzpicture}",
        "solution": [ { "math": "\\text{Left} = \\text{sum of right verticals}", "note": "$2 + 4$" }, { "math": "$= 6 \\text{ cm}$", "note": "" } ] },
      { "q": "A rectangle's perimeter is being found. The two lengths total $24$ cm and one width is $5$ cm. Find the perimeter.", "a": "$34$ cm",
        "tikz": "\\begin{tikzpicture}[x=1cm,y=1cm]\n\\draw[thick] (0,0) rectangle (4,1.4);\n\\node[above] at (2,1.4) {$12\\text{ cm}$};\n\\node[right] at (4,0.7) {$5\\text{ cm}$};\n\\end{tikzpicture}",
        "solution": [ { "math": "\\text{Lengths } 24,\\ \\text{widths } 2 \\times 5", "note": "" }, { "math": "$24 + 10 = 34 \\text{ cm}$", "note": "" } ] },
      { "q": "An equilateral triangle has one side $13$ cm marked. Find the perimeter without measuring the others.", "a": "$39$ cm",
        "tikz": "\\begin{tikzpicture}[x=1cm,y=1cm]\n\\draw[thick] (0,0)--(4,0)--(2,3.4)--cycle;\n\\node[below] at (2,0) {$13\\text{ cm}$};\n\\node[left] at (0.8,1.7) {$?$};\n\\node[right] at (3.2,1.7) {$?$};\n\\end{tikzpicture}",
        "solution": [ { "math": "\\text{All sides} = 13", "note": "Equilateral" }, { "math": "$3 \\times 13 = 39 \\text{ cm}$", "note": "" } ] }
    ],
    "mastery": [
      { "q": "On this L-shape, find the missing horizontal side $a$, then the perimeter (cm).", "a": "$a = 4$ cm; perimeter $24$ cm",
        "tikz": "\\begin{tikzpicture}[x=0.6cm,y=0.6cm]\n\\draw[thick] (0,0)--(7,0)--(7,3)--(3,3)--(3,5)--(0,5)--cycle;\n\\node[below] at (3.5,0) {$7$};\n\\node[right] at (7,1.5) {$3$};\n\\node[above] at (5,3) {$a$};\n\\node[right] at (3,4) {$2$};\n\\node[above] at (1.5,5) {$3$};\n\\node[left] at (0,2.5) {$5$};\n\\end{tikzpicture}",
        "solution": [ { "math": "$a = 7 - 3 = 4$", "note": "Top steps span the base" }, { "math": "$7+3+4+2+3+5 = 24 \\text{ cm}$", "note": "" } ] },
      { "q": "A rectangle has only its length $20$ cm marked. Its width is half the length. Find the perimeter.", "a": "$60$ cm",
        "tikz": "\\begin{tikzpicture}[x=1cm,y=1cm]\n\\draw[thick] (0,0) rectangle (4,1.6);\n\\node[below] at (2,0) {$20\\text{ cm}$};\n\\node[right] at (4,0.8) {$?$};\n\\end{tikzpicture}",
        "solution": [ { "math": "\\text{width} = 20 \\div 2 = 10", "note": "Half the length" }, { "math": "$2 \\times (20 + 10) = 60 \\text{ cm}$", "note": "" } ] },
      { "q": "On this L-shape, find missing vertical side $b$, then the perimeter (m).", "a": "$b = 3$ m; perimeter $28$ m",
        "tikz": "\\begin{tikzpicture}[x=0.55cm,y=0.55cm]\n\\draw[thick] (0,0)--(8,0)--(8,3)--(3,3)--(3,6)--(0,6)--cycle;\n\\node[below] at (4,0) {$8$};\n\\node[right] at (8,1.5) {$b$};\n\\node[above] at (5.5,3) {$5$};\n\\node[right] at (3,4.5) {$3$};\n\\node[above] at (1.5,6) {$3$};\n\\node[left] at (0,3) {$6$};\n\\end{tikzpicture}",
        "solution": [ { "math": "$b = 6 - 3 = 3$", "note": "Right verticals total the left" }, { "math": "$8+3+5+3+3+6 = 28 \\text{ m}$", "note": "" } ] },
      { "q": "A square and a rectangle share a side. The square's side is $6$ cm; the rectangle is $6$ cm by $10$ cm. Using only equal sides, find the rectangle's perimeter.", "a": "$32$ cm",
        "tikz": "\\begin{tikzpicture}[x=0.5cm,y=0.5cm]\n\\draw[thick] (0,0) rectangle (6,6);\n\\draw[thick] (6,0) rectangle (16,6);\n\\node[below] at (3,0) {$6$};\n\\node[below] at (11,0) {$10$};\n\\node[right] at (16,3) {$6$};\n\\end{tikzpicture}",
        "solution": [ { "math": "\\text{rectangle } 10 \\times 6", "note": "Shares the 6 cm side" }, { "math": "$2 \\times (10 + 6) = 32 \\text{ cm}$", "note": "" } ] },
      { "q": "A rectangle's perimeter is $40$ cm. Only the length $14$ cm is marked. Find the unmarked width.", "a": "$6$ cm",
        "tikz": "\\begin{tikzpicture}[x=1cm,y=1cm]\n\\draw[thick] (0,0) rectangle (4,1.4);\n\\node[below] at (2,0) {$14\\text{ cm}$};\n\\node[right] at (4,0.7) {$?$};\n\\end{tikzpicture}",
        "solution": [ { "math": "$40 \\div 2 = 20 = \\ell + w$", "note": "Half the perimeter" }, { "math": "$20 - 14 = 6 \\text{ cm}$", "note": "" } ] },
      { "q": "Which is the smallest number of measurements needed to find the perimeter of a regular hexagon (all sides equal)?", "a": "$1$ measurement",
        "solution": [ { "math": "\\text{All 6 sides equal}", "note": "Regular" }, { "math": "$1 \\text{ side} \\times 6", "note": "One measurement is enough" } ] },
      { "q": "A rectangular pool deck has outer length $12$ m and width $8$ m. Only those two are marked. Find the perimeter to fence it.", "a": "$40$ m",
        "tikz": "\\begin{tikzpicture}[x=1cm,y=1cm]\n\\draw[thick] (0,0) rectangle (4,2.4);\n\\node[below] at (2,0) {$12\\text{ m}$};\n\\node[right] at (4,1.2) {$8\\text{ m}$};\n\\end{tikzpicture}",
        "solution": [ { "math": "\\text{Opposite sides equal}", "note": "12, 8, 12, 8" }, { "math": "$2 \\times (12 + 8) = 40 \\text{ m}$", "note": "" } ] },
      { "q": "On this L-shape every right angle is shown but two sides are blank. If the full base is $9$ cm and the lower-left height is $5$ cm, and the notch is $4$ cm wide and $2$ cm tall, find the perimeter (cm).", "a": "$28$ cm",
        "tikz": "\\begin{tikzpicture}[x=0.55cm,y=0.55cm]\n\\draw[thick] (0,0)--(9,0)--(9,3)--(5,3)--(5,5)--(0,5)--cycle;\n\\node[below] at (4.5,0) {$9$};\n\\node[left] at (0,2.5) {$5$};\n\\node[above] at (2.5,5) {$5$};\n\\node[right] at (5,4) {$2$};\n\\node[above] at (7,3) {$4$};\n\\node[right] at (9,1.5) {$3$};\n\\end{tikzpicture}",
        "solution": [ { "math": "\\text{Blanks: top} = 9-4 = 5,\\ \\text{right} = 5-2 = 3", "note": "From equal totals" }, { "math": "$9+5+5+2+4+3 = 28 \\text{ cm}$", "note": "" } ] },
      { "q": "A square tile of side $s$ has perimeter $48$ cm. A second tile has side $2s$. Find the second tile's perimeter.", "a": "$96$ cm",
        "solution": [ { "math": "$s = 48 \\div 4 = 12$", "note": "First side" }, { "math": "$4 \\times (2 \\times 12) = 96 \\text{ cm}$", "note": "" } ] },
      { "q": "A rectangle has length $3$ times its width and perimeter $32$ cm. Find both side lengths.", "a": "width $4$ cm, length $12$ cm",
        "solution": [ { "math": "$2(3w + w) = 32$", "note": "length $= 3w$" }, { "math": "$8w = 32 \\Rightarrow w = 4,\\ \\ell = 12 \\text{ cm}$", "note": "" } ] }
    ]
  }
}
